pio/__init__.py
pio/__main__.py
pio/pio.py
pio_cli-0.87.dist-info/DESCRIPTION.rst
pio_cli-0.87.dist-info/METADATA
pio_cli-0.87.dist-info/RECORD
pio_cli-0.87.dist-info/WHEEL
pio_cli-0.87.dist-info/entry_points.txt
pio_cli-0.87.dist-info/metadata.json
pio_cli-0.87.dist-info/top_level.txt
