Metadata-Version: 2.0
Name: pio-cli
Version: 0.87
Summary: PipelineAI CLI
Home-page: https://github.com/fluxcapacitor/pipeline/cli
Author: Chris Fregly
Author-email: chris@pipeline.io
License: UNKNOWN
Platform: UNKNOWN
Requires-Dist: fire (==0.1.1)
Requires-Dist: futures (==3.1.1)
Requires-Dist: kubernetes (==3.0.0a1)
Requires-Dist: pyyaml (==3.12)
Requires-Dist: requests (==2.18.1)
Requires-Dist: tabulate (==0.7.7)
